location_guessing_game_telegram_bot/__init__.py
location_guessing_game_telegram_bot-0.1.1.dist-info/COPYING
location_guessing_game_telegram_bot-0.1.1.dist-info/METADATA
location_guessing_game_telegram_bot-0.1.1.dist-info/WHEEL
location_guessing_game_telegram_bot-0.1.1.dist-info/entry_points.txt
location_guessing_game_telegram_bot-0.1.1.dist-info/top_level.txt
location_guessing_game_telegram_bot-0.1.1.dist-info/RECORD
