Metadata-Version: 2.1
Name: location-guessing-game-telegram-bot
Version: 0.1.1
Summary: Basic Telegram Bot Sending Random Wikimedia Commons Photos
Home-page: https://github.com/fphammerle/location-guessing-game-telegram-bot
Author: Fabian Peter Hammerle
Author-email: fabian+location-guessing@hammerle.me
License: GPLv3+
Project-URL: Changelog, https://github.com/fphammerle/location-guessing-game-telegram-bot/blob/master/CHANGELOG.md
Keywords: bot,game,guessing,location,photos,telegram
Platform: UNKNOWN
Classifier: Development Status :: 3 - Alpha
Classifier: Intended Audience :: End Users/Desktop
Classifier: License :: OSI Approved :: GNU General Public License v3 or later (GPLv3+)
Classifier: Operating System :: OS Independent
Classifier: Topic :: Games/Entertainment
Classifier: Programming Language :: Python :: 3.5
Classifier: Programming Language :: Python :: 3.6
Classifier: Programming Language :: Python :: 3.7
Classifier: Programming Language :: Python :: 3.8
Classifier: Programming Language :: Python :: 3.9
Requires-Dist: python-telegram-bot
